AUTHORS
ChangeLog
LICENSE
MANIFEST.in
README.rst
requirements.txt
setup.cfg
setup.py
leonardo_hijack/__init__.py
leonardo_hijack/models.py
leonardo_hijack/settings.py
leonardo_hijack/urls.py
leonardo_hijack.egg-info/PKG-INFO
leonardo_hijack.egg-info/SOURCES.txt
leonardo_hijack.egg-info/dependency_links.txt
leonardo_hijack.egg-info/not-zip-safe
leonardo_hijack.egg-info/pbr.json
leonardo_hijack.egg-info/requires.txt
leonardo_hijack.egg-info/top_level.txt
leonardo_hijack/static/hijack/leonardo-hijack-styles.css
requirements/default.txt